pythonmysequel/Connection.py
pythonmysequel/Row.py
pythonmysequel/SQLite_Connection.py
pythonmysequel/Table.py
pythonmysequel/__init__.py
pythonmysequel/values/Bool.py
pythonmysequel/values/Float.py
pythonmysequel/values/Int.py
pythonmysequel/values/String.py
pythonmysequel/values/_ValueType.py
pythonmysequel/values/__init__.py
PythonMySequel-0.2.2.dist-info/LICENSE
PythonMySequel-0.2.2.dist-info/METADATA
PythonMySequel-0.2.2.dist-info/WHEEL
PythonMySequel-0.2.2.dist-info/top_level.txt
PythonMySequel-0.2.2.dist-info/RECORD
