Metadata-Version: 2.1
Name: PythonMySequel
Version: 0.2.2
Summary: An easier to use MySQL/SQLite connector for Python.
Home-page: https://github.com/jasonli0616/PythonMySequel
Author: Jason Li
License: MIT
Project-URL: Bug Tracker, https://github.com/jasonli0616/PythonMySequel/issues
Platform: UNKNOWN
Classifier: Programming Language :: Python :: 3
Classifier: License :: OSI Approved :: MIT License
Classifier: Operating System :: OS Independent
Requires-Python: >=3.6
License-File: LICENSE
Requires-Dist: mysql-connector-python (==8.0.26)
Requires-Dist: protobuf (==3.17.3)
Requires-Dist: six (==1.16.0)
